{
  "m_GameObject": {
    "m_FileID": 0,
    "m_PathID": 0
  },
  "m_Enabled": 1,
  "m_Script": {
    "m_FileID": 0,
    "m_PathID": 8302033850027404168
  },
  "m_Name": "NPC_90091_SkeletonData",
  "atlasAssets": [
    {
      "m_FileID": 0,
      "m_PathID": 5352042519783944420
    }
  ],
  "scale": 0.25,
  "skeletonJSON": {
    "m_FileID": 0,
    "m_PathID": -1157372231461022166
  },
  "fromAnimation": [],
  "toAnimation": [],
  "duration": [],
  "defaultMix": 0.2,
  "controller": {
    "m_FileID": 0,
    "m_PathID": 0
  }
}