{
  "m_GameObject": {
    "m_FileID": 0,
    "m_PathID": 0
  },
  "m_Enabled": 1,
  "m_Script": {
    "m_FileID": 0,
    "m_PathID": 8302033850027404168
  },
  "m_Name": "npc_1510_SkeletonData",
  "atlasAssets": [
    {
      "m_FileID": 0,
      "m_PathID": -71179825318730805
    }
  ],
  "scale": 0.33,
  "skeletonJSON": {
    "m_FileID": 0,
    "m_PathID": 5334532590071211721
  },
  "fromAnimation": [],
  "toAnimation": [],
  "duration": [],
  "defaultMix": 0.2,
  "controller": {
    "m_FileID": 0,
    "m_PathID": 0
  }
}