{
  "m_GameObject": {
    "m_FileID": 0,
    "m_PathID": 0
  },
  "m_Enabled": 1,
  "m_Script": {
    "m_FileID": 0,
    "m_PathID": 8302033850027404168
  },
  "m_Name": "Figure_1729_SkeletonData",
  "atlasAssets": [
    {
      "m_FileID": 0,
      "m_PathID": -1220030475833256489
    }
  ],
  "scale": 0.25,
  "skeletonJSON": {
    "m_FileID": 0,
    "m_PathID": -6511972400582652867
  },
  "fromAnimation": [],
  "toAnimation": [],
  "duration": [],
  "defaultMix": 0.2,
  "controller": {
    "m_FileID": 0,
    "m_PathID": 8811637370539239075
  }
}