{
  "m_GameObject": {
    "m_FileID": 0,
    "m_PathID": 0
  },
  "m_Enabled": 1,
  "m_Script": {
    "m_FileID": 0,
    "m_PathID": 8302033850027404168
  },
  "m_Name": "Renouyi_Q_SkeletonData",
  "atlasAssets": [
    {
      "m_FileID": 0,
      "m_PathID": -1747959626831374346
    }
  ],
  "scale": 0.2,
  "skeletonJSON": {
    "m_FileID": 0,
    "m_PathID": 4307967321360723485
  },
  "fromAnimation": [],
  "toAnimation": [],
  "duration": [],
  "defaultMix": 0.2,
  "controller": {
    "m_FileID": 0,
    "m_PathID": -2189920654562230364
  }
}