{
  "m_GameObject": {
    "m_FileID": 0,
    "m_PathID": 0
  },
  "m_Enabled": 1,
  "m_Script": {
    "m_FileID": 0,
    "m_PathID": 8302033850027404168
  },
  "m_Name": "younianboshi_SkeletonData",
  "atlasAssets": [
    {
      "m_FileID": 0,
      "m_PathID": -4862315751019180940
    }
  ],
  "scale": 0.2,
  "skeletonJSON": {
    "m_FileID": 0,
    "m_PathID": 3702912690539952908
  },
  "fromAnimation": [],
  "toAnimation": [],
  "duration": [],
  "defaultMix": 0.2,
  "controller": {
    "m_FileID": 0,
    "m_PathID": -6492958834640304582
  }
}